baboTest/exercise_07.py
baboTest/test1.py
baboTest/test2.py
baboTest-0.0.0.3.dist-info/METADATA
baboTest-0.0.0.3.dist-info/WHEEL
baboTest-0.0.0.3.dist-info/top_level.txt
baboTest-0.0.0.3.dist-info/RECORD
