Metadata-Version: 2.1
Name: baboTest
Version: 0.0.0.3
Summary: My First Test Package
Home-page: https://naver.com
Author: HanSu Kim
Author-email: gimhansu@naver.com
License: MIT
Platform: UNKNOWN
Requires-Python: >=3
